Metadata-Version: 1.1
Name: pypi-interface
Version: 0.1.1
Summary: pypi-interface is meant to serve as a client for pypi use
Home-page: https://github.com/shir0kamii/pypi-interface
Author: Alexandre Bonnetain
Author-email: alexandrebonnetain@gmail.com
License: UNKNOWN
Download-URL: https://github.com/shir0kamii/pypi-interface/tags
Platform: any
Classifier: Operating System :: POSIX :: Linux
Classifier: Programming Language :: Python :: 3
Classifier: Programming Language :: Python :: 3.2
Classifier: Programming Language :: Python :: 3.3
Classifier: Programming Language :: Python :: 3.4
Classifier: Programming Language :: Python :: 3.5
Classifier: Topic :: Software Development :: Libraries :: Python Modules
